MANIFEST.in
README.rst
setup.py
eurovision/__init__.py
eurovision/cli.py
eurovision/eurovision.py
eurovision/person.py
eurovision/utils.py
eurovision/data/countries-2016.csv
eurovision/tests/__init__.py
eurovision/tests/test_eurovision.py
eurovision/tests/test_person.py
eurovision/tests/test_utils.py
eurovision_country_selector.egg-info/PKG-INFO
eurovision_country_selector.egg-info/SOURCES.txt
eurovision_country_selector.egg-info/dependency_links.txt
eurovision_country_selector.egg-info/entry_points.txt
eurovision_country_selector.egg-info/top_level.txt
examples/example_names_with_country_exclusion.csv
examples/example_output.csv