Metadata-Version: 1.1
Name: eurovision-country-selector
Version: 1.0.5.2016
Summary: Select a country for your EuroVision party.
Home-page: https://github.com/mikejarrett/eurovision-country-selector
Author: Mike Jarrett
Author-email: mike<dot>d<dot>jarrett<at>gmail<dot>com
License: MIT
Platform: UNKNOWN
Classifier: Development Status :: 5 - Production/Stable
Classifier: Intended Audience :: End Users/Desktop
Classifier: Programming Language :: Python :: 2.7
Classifier: Programming Language :: Python :: 3
Classifier: Programming Language :: Python :: 3.0
Classifier: Programming Language :: Python :: 3.1
Classifier: Programming Language :: Python :: 3.4
Classifier: Programming Language :: Python :: 3.5
Classifier: Operating System :: POSIX :: Linux
